<?xml version="1.0" encoding="utf-8"?>
<!DOCTYPE hibernate-mapping PUBLIC "-//Hibernate/Hibernate Mapping DTD 3.0//EN"
"http://www.hibernate.org/dtd/hibernate-mapping-3.0.dtd">
<!-- 
    Mapping file autogenerated by MyEclipse Persistence Tools
-->
<hibernate-mapping>
    <class name="com.axp.domain.AdvertDaysChangeLog" table="advert_days_change_log"  >
        <id name="id" type="java.lang.Integer">
            <column name="id" />
             <generator class="identity" />
        </id>
        <many-to-one name="adminUser" class="com.axp.domain.AdminUser" fetch="select" >
            <column name="userId">
                <comment>上传用户ID</comment>
            </column>
        </many-to-one>
        <property name="parentId" type="java.lang.Integer">
            <column name="parentId">
                <comment>上级id</comment>
            </column>
        </property>
        <property name="userRealName" type="java.lang.String">
            <column name="userRealName" length="32">
                <comment>真实姓名</comment>
            </column>
        </property>
        <property name="centerDayCounts" type="java.lang.Integer">
            <column name="centerDayCounts">
                <comment>运营中心广告天数</comment>
            </column>
        </property>
        <property name="cityDayCounts" type="java.lang.Integer">
            <column name="cityDayCounts">
                <comment>城市代理广告天数</comment>
            </column>
        </property>
        <property name="unionDaycounts" type="java.lang.Integer">
            <column name="unionDaycounts">
                <comment>联盟组广告天数</comment>
            </column>
        </property>
        <property name="createTime" type="java.sql.Timestamp">
            <column name="createTime" length="19" />
        </property>
        <property name="discript" type="java.lang.String">
            <column name="discript" length="32">
                <comment>描述</comment>
            </column>
        </property>
    </class>
</hibernate-mapping>
